atcommander/__init__.py
atcommander/__main__.py
atcommander/arg_parser.py
atcommander/main.py
atcommander-0.1.0.dist-info/entry_points.txt
atcommander-0.1.0.dist-info/WHEEL
atcommander-0.1.0.dist-info/METADATA
atcommander-0.1.0.dist-info/RECORD
