Metadata-Version: 2.1
Name: atcommander
Version: 0.1.0
Summary: A simple AT Command tool
Author: helloysd
Author-email: helloysd@foxmail.com
Requires-Python: >=3.8,<4.0
Classifier: Programming Language :: Python :: 3
Classifier: Programming Language :: Python :: 3.8
Classifier: Programming Language :: Python :: 3.9
Classifier: Programming Language :: Python :: 3.10
Requires-Dist: importlib-metadata (>=1.0,<2.0); python_version < "3.8"
Requires-Dist: pyserial (>=3.5,<4.0)
Requires-Dist: requests (>=2.28.1,<3.0.0)
